{"boards": [
{ "board": "espressif:esp32:esp32",
                "target": "esp32",
                "sketches": [
{"name": "libraries/Zigbee/examples/Zigbee_Multistate_Input_Output",
                    "sizes": [{
                            "flash_bytes": 641176,
                            "flash_percentage": 48,
                            "ram_bytes": 38340,
                            "ram_percentage": 11
                            }]
                    },
{"name": "libraries/Zigbee/examples/Zigbee_On_Off_MultiSwitch",
                    "sizes": [{
                            "flash_bytes": 658924,
                            "flash_percentage": 50,
                            "ram_bytes": 38364,
                            "ram_percentage": 11
                            }]
                    },
{"name": "libraries/Zigbee/examples/Zigbee_On_Off_Switch",
                    "sizes": [{
                            "flash_bytes": 650204,
                            "flash_percentage": 49,
                            "ram_bytes": 38780,
                            "ram_percentage": 11
                            }]
                    },
{"name": "libraries/Zigbee/examples/Zigbee_Power_Outlet",
                    "sizes": [{
                            "flash_bytes": 645016,
                            "flash_percentage": 49,
                            "ram_bytes": 38268,
                            "ram_percentage": 11
                            }]
                    },
{"name": "libraries/Zigbee/examples/Zigbee_Range_Extender",
                    "sizes": [{
                            "flash_bytes": 637224,
                            "flash_percentage": 48,
                            "ram_bytes": 38204,
                            "ram_percentage": 11
                            }]
                    },
{"name": "libraries/Zigbee/examples/Zigbee_Thermostat",
                    "sizes": [{
                            "flash_bytes": 659386,
                            "flash_percentage": 50,
                            "ram_bytes": 38744,
                            "ram_percentage": 11
                            }]
                    }
]
},
{ "board": "espressif:esp32:esp32c3",
                "target": "esp32c3",
                "sketches": [
{"name": "libraries/Zigbee/examples/Zigbee_On_Off_MultiSwitch",
                    "sizes": [{
                            "flash_bytes": 678662,
                            "flash_percentage": 51,
                            "ram_bytes": 29668,
                            "ram_percentage": 9
                            }]
                    },
{"name": "libraries/Zigbee/examples/Zigbee_On_Off_Switch",
                    "sizes": [{
                            "flash_bytes": 667638,
                            "flash_percentage": 50,
                            "ram_bytes": 29868,
                            "ram_percentage": 9
                            }]
                    },
{"name": "libraries/Zigbee/examples/Zigbee_Power_Outlet",
                    "sizes": [{
                            "flash_bytes": 681596,
                            "flash_percentage": 52,
                            "ram_bytes": 30352,
                            "ram_percentage": 9
                            }]
                    },
{"name": "libraries/Zigbee/examples/Zigbee_Range_Extender",
                    "sizes": [{
                            "flash_bytes": 672232,
                            "flash_percentage": 51,
                            "ram_bytes": 30288,
                            "ram_percentage": 9
                            }]
                    },
{"name": "libraries/Zigbee/examples/Zigbee_Thermostat",
                    "sizes": [{
                            "flash_bytes": 676340,
                            "flash_percentage": 51,
                            "ram_bytes": 29780,
                            "ram_percentage": 9
                            }]
                    }
]
},
{ "board": "espressif:esp32:esp32c5",
                "target": "esp32c5",
                "sketches": [
{"name": "libraries/Zigbee/examples/Zigbee_Temperature_Sensor",
                    "sizes": [{
                            "flash_bytes": 668949,
                            "flash_percentage": 51,
                            "ram_bytes": 36932,
                            "ram_percentage": 11
                            }]
                    },
{"name": "libraries/Zigbee/examples/Zigbee_Thermostat",
                    "sizes": [{
                            "flash_bytes": 774401,
                            "flash_percentage": 59,
                            "ram_bytes": 40460,
                            "ram_percentage": 12
                            }]
                    },
{"name": "libraries/Zigbee/examples/Zigbee_Vibration_Sensor",
                    "sizes": [{
                            "flash_bytes": 638641,
                            "flash_percentage": 48,
                            "ram_bytes": 36764,
                            "ram_percentage": 11
                            }]
                    },
{"name": "libraries/Zigbee/examples/Zigbee_Wind_Speed_Sensor",
                    "sizes": [{
                            "flash_bytes": 639991,
                            "flash_percentage": 48,
                            "ram_bytes": 36756,
                            "ram_percentage": 11
                            }]
                    },
{"name": "libraries/Zigbee/examples/Zigbee_Window_Covering",
                    "sizes": [{
                            "flash_bytes": 647157,
                            "flash_percentage": 49,
                            "ram_bytes": 36828,
                            "ram_percentage": 11
                            }]
                    }
]
},
{ "board": "espressif:esp32:esp32c6",
                "target": "esp32c6",
                "sketches": [
{"name": "libraries/Zigbee/examples/Zigbee_Temp_Hum_Sensor_Sleepy",
                    "sizes": [{
                            "flash_bytes": 595812,
                            "flash_percentage": 45,
                            "ram_bytes": 32396,
                            "ram_percentage": 9
                            }]
                    },
{"name": "libraries/Zigbee/examples/Zigbee_Temperature_Sensor",
                    "sizes": [{
                            "flash_bytes": 594224,
                            "flash_percentage": 45,
                            "ram_bytes": 32332,
                            "ram_percentage": 9
                            }]
                    },
{"name": "libraries/Zigbee/examples/Zigbee_Thermostat",
                    "sizes": [{
                            "flash_bytes": 706134,
                            "flash_percentage": 53,
                            "ram_bytes": 35884,
                            "ram_percentage": 10
                            }]
                    },
{"name": "libraries/Zigbee/examples/Zigbee_Vibration_Sensor",
                    "sizes": [{
                            "flash_bytes": 580368,
                            "flash_percentage": 44,
                            "ram_bytes": 32184,
                            "ram_percentage": 9
                            }]
                    },
{"name": "libraries/Zigbee/examples/Zigbee_Wind_Speed_Sensor",
                    "sizes": [{
                            "flash_bytes": 581712,
                            "flash_percentage": 44,
                            "ram_bytes": 32152,
                            "ram_percentage": 9
                            }]
                    },
{"name": "libraries/Zigbee/examples/Zigbee_Window_Covering",
                    "sizes": [{
                            "flash_bytes": 588900,
                            "flash_percentage": 44,
                            "ram_bytes": 32248,
                            "ram_percentage": 9
                            }]
                    }
]
},
{ "board": "espressif:esp32:esp32h2",
                "target": "esp32h2",
                "sketches": [
{"name": "libraries/Zigbee/examples/Zigbee_Range_Extender",
                    "sizes": [{
                            "flash_bytes": 708101,
                            "flash_percentage": 54,
                            "ram_bytes": 34880,
                            "ram_percentage": 10
                            }]
                    },
{"name": "libraries/Zigbee/examples/Zigbee_Scan_Networks",
                    "sizes": [{
                            "flash_bytes": 535835,
                            "flash_percentage": 40,
                            "ram_bytes": 29844,
                            "ram_percentage": 9
                            }]
                    },
{"name": "libraries/Zigbee/examples/Zigbee_Temp_Hum_Sensor_Sleepy",
                    "sizes": [{
                            "flash_bytes": 593633,
                            "flash_percentage": 45,
                            "ram_bytes": 30848,
                            "ram_percentage": 9
                            }]
                    },
{"name": "libraries/Zigbee/examples/Zigbee_Temperature_Sensor",
                    "sizes": [{
                            "flash_bytes": 607893,
                            "flash_percentage": 46,
                            "ram_bytes": 30852,
                            "ram_percentage": 9
                            }]
                    },
{"name": "libraries/Zigbee/examples/Zigbee_Thermostat",
                    "sizes": [{
                            "flash_bytes": 712649,
                            "flash_percentage": 54,
                            "ram_bytes": 34396,
                            "ram_percentage": 10
                            }]
                    },
{"name": "libraries/Zigbee/examples/Zigbee_Vibration_Sensor",
                    "sizes": [{
                            "flash_bytes": 585753,
                            "flash_percentage": 44,
                            "ram_bytes": 30716,
                            "ram_percentage": 9
                            }]
                    },
{"name": "libraries/Zigbee/examples/Zigbee_Wind_Speed_Sensor",
                    "sizes": [{
                            "flash_bytes": 578979,
                            "flash_percentage": 44,
                            "ram_bytes": 30668,
                            "ram_percentage": 9
                            }]
                    },
{"name": "libraries/Zigbee/examples/Zigbee_Window_Covering",
                    "sizes": [{
                            "flash_bytes": 585869,
                            "flash_percentage": 44,
                            "ram_bytes": 30748,
                            "ram_percentage": 9
                            }]
                    }
]
},
{ "board": "espressif:esp32:esp32p4",
                "target": "esp32p4",
                "sketches": [
{"name": "libraries/WiFi/examples/WiFiUDPClient",
                    "sizes": [{
                            "flash_bytes": 858772,
                            "flash_percentage": 65,
                            "ram_bytes": 31676,
                            "ram_percentage": 9
                            }]
                    },
{"name": "libraries/Wire/examples/WireMaster",
                    "sizes": [{
                            "flash_bytes": 350152,
                            "flash_percentage": 26,
                            "ram_bytes": 25340,
                            "ram_percentage": 7
                            }]
                    },
{"name": "libraries/Wire/examples/WireScan",
                    "sizes": [{
                            "flash_bytes": 349886,
                            "flash_percentage": 26,
                            "ram_bytes": 25340,
                            "ram_percentage": 7
                            }]
                    },
{"name": "libraries/Wire/examples/WireSlave",
                    "sizes": [{
                            "flash_bytes": 350500,
                            "flash_percentage": 26,
                            "ram_bytes": 25340,
                            "ram_percentage": 7
                            }]
                    },
{"name": "libraries/Wire/examples/WireSlaveFunctionalCallback",
                    "sizes": [{
                            "flash_bytes": 350396,
                            "flash_percentage": 26,
                            "ram_bytes": 25340,
                            "ram_percentage": 7
                            }]
                    }
]
},
{ "board": "espressif:esp32:esp32s2",
                "target": "esp32s2",
                "sketches": [
{"name": "libraries/Zigbee/examples/Zigbee_Analog_Input_Output",
                    "sizes": [{
                            "flash_bytes": 611752,
                            "flash_percentage": 46,
                            "ram_bytes": 33328,
                            "ram_percentage": 10
                            }]
                    },
{"name": "libraries/Zigbee/examples/Zigbee_Color_Dimmer_Switch",
                    "sizes": [{
                            "flash_bytes": 618788,
                            "flash_percentage": 47,
                            "ram_bytes": 33016,
                            "ram_percentage": 10
                            }]
                    },
{"name": "libraries/Zigbee/examples/Zigbee_Electrical_AC_Sensor",
                    "sizes": [{
                            "flash_bytes": 613400,
                            "flash_percentage": 46,
                            "ram_bytes": 33040,
                            "ram_percentage": 10
                            }]
                    },
{"name": "libraries/Zigbee/examples/Zigbee_Electrical_AC_Sensor_MultiPhase",
                    "sizes": [{
                            "flash_bytes": 613312,
                            "flash_percentage": 46,
                            "ram_bytes": 33040,
                            "ram_percentage": 10
                            }]
                    },
{"name": "libraries/Zigbee/examples/Zigbee_Fan_Control",
                    "sizes": [{
                            "flash_bytes": 615205,
                            "flash_percentage": 46,
                            "ram_bytes": 33092,
                            "ram_percentage": 10
                            }]
                    },
{"name": "libraries/Zigbee/examples/Zigbee_Gateway",
                    "sizes": [{
                            "flash_bytes": 1199739,
                            "flash_percentage": 35,
                            "ram_bytes": 57756,
                            "ram_percentage": 17
                            }]
                    },
{"name": "libraries/Zigbee/examples/Zigbee_Multistate_Input_Output",
                    "sizes": [{
                            "flash_bytes": 601336,
                            "flash_percentage": 45,
                            "ram_bytes": 33048,
                            "ram_percentage": 10
                            }]
                    },
{"name": "libraries/Zigbee/examples/Zigbee_On_Off_MultiSwitch",
                    "sizes": [{
                            "flash_bytes": 618912,
                            "flash_percentage": 47,
                            "ram_bytes": 33072,
                            "ram_percentage": 10
                            }]
                    },
{"name": "libraries/Zigbee/examples/Zigbee_On_Off_Switch",
                    "sizes": [{
                            "flash_bytes": 610488,
                            "flash_percentage": 46,
                            "ram_bytes": 33568,
                            "ram_percentage": 10
                            }]
                    },
{"name": "libraries/Zigbee/examples/Zigbee_Power_Outlet",
                    "sizes": [{
                            "flash_bytes": 622041,
                            "flash_percentage": 47,
                            "ram_bytes": 33148,
                            "ram_percentage": 10
                            }]
                    },
{"name": "libraries/Zigbee/examples/Zigbee_Range_Extender",
                    "sizes": [{
                            "flash_bytes": 614249,
                            "flash_percentage": 46,
                            "ram_bytes": 33084,
                            "ram_percentage": 10
                            }]
                    },
{"name": "libraries/Zigbee/examples/Zigbee_Thermostat",
                    "sizes": [{
                            "flash_bytes": 619316,
                            "flash_percentage": 47,
                            "ram_bytes": 33168,
                            "ram_percentage": 10
                            }]
                    }
]
},
{ "board": "espressif:esp32:esp32s3",
                "target": "esp32s3",
                "sketches": [
{"name": "libraries/Zigbee/examples/Zigbee_Electrical_AC_Sensor_MultiPhase",
                    "sizes": [{
                            "flash_bytes": 649149,
                            "flash_percentage": 49,
                            "ram_bytes": 38620,
                            "ram_percentage": 11
                            }]
                    },
{"name": "libraries/Zigbee/examples/Zigbee_Fan_Control",
                    "sizes": [{
                            "flash_bytes": 656238,
                            "flash_percentage": 50,
                            "ram_bytes": 38508,
                            "ram_percentage": 11
                            }]
                    },
{"name": "libraries/Zigbee/examples/Zigbee_Gateway",
                    "sizes": [{
                            "flash_bytes": 1231234,
                            "flash_percentage": 36,
                            "ram_bytes": 61888,
                            "ram_percentage": 18
                            }]
                    },
{"name": "libraries/Zigbee/examples/Zigbee_Multistate_Input_Output",
                    "sizes": [{
                            "flash_bytes": 635789,
                            "flash_percentage": 48,
                            "ram_bytes": 38468,
                            "ram_percentage": 11
                            }]
                    },
{"name": "libraries/Zigbee/examples/Zigbee_On_Off_MultiSwitch",
                    "sizes": [{
                            "flash_bytes": 653105,
                            "flash_percentage": 49,
                            "ram_bytes": 38476,
                            "ram_percentage": 11
                            }]
                    },
{"name": "libraries/Zigbee/examples/Zigbee_On_Off_Switch",
                    "sizes": [{
                            "flash_bytes": 645105,
                            "flash_percentage": 49,
                            "ram_bytes": 39020,
                            "ram_percentage": 11
                            }]
                    },
{"name": "libraries/Zigbee/examples/Zigbee_Power_Outlet",
                    "sizes": [{
                            "flash_bytes": 663122,
                            "flash_percentage": 50,
                            "ram_bytes": 38564,
                            "ram_percentage": 11
                            }]
                    },
{"name": "libraries/Zigbee/examples/Zigbee_Range_Extender",
                    "sizes": [{
                            "flash_bytes": 655242,
                            "flash_percentage": 49,
                            "ram_bytes": 38500,
                            "ram_percentage": 11
                            }]
                    },
{"name": "libraries/Zigbee/examples/Zigbee_Thermostat",
                    "sizes": [{
                            "flash_bytes": 654049,
                            "flash_percentage": 49,
                            "ram_bytes": 38604,
                            "ram_percentage": 11
                            }]
                    }
]
}
]}
